str_macros/__init__.py
str_macros/context_manager.py
str_macros/decorator.py
str_macros/mixins.py
str_macros-0.1.dist-info/DESCRIPTION.rst
str_macros-0.1.dist-info/LICENSE.txt
str_macros-0.1.dist-info/METADATA
str_macros-0.1.dist-info/RECORD
str_macros-0.1.dist-info/WHEEL
str_macros-0.1.dist-info/metadata.json
str_macros-0.1.dist-info/top_level.txt
