Metadata-Version: 2.0
Name: str-macros
Version: 0.1
Summary: Macros (variables) for str class attributes
Home-page: https://github.com/abramovd/str-macros
Author: Dmitry Abramov
Author-email: diabramo@yandex.ru
License: MIT
Keywords: python django str macros
Platform: UNKNOWN
Classifier: Development Status :: 3 - Alpha
Classifier: Intended Audience :: Developers
Classifier: Topic :: Software Development :: Libraries
Classifier: License :: OSI Approved :: Apache Software License
Classifier: Programming Language :: Python :: 2.7
Classifier: Programming Language :: Python :: 3.5
